{"year":"2016","month":"6","permalink":"http:/catlittlechen.com/archives/2016/6","_total":2,"_totalPage":1,"_page":1,"posts":[{"tags":[{"name":"生活","permalink":"http://catlittlechen.com/tags/生活/","url":"/async/tags/生活.json","count":3}],"categories":[{"name":"活着","permalink":"http://catlittlechen.com/categories/活着/","url":"/async/categories/活着.json","count":3}],"url":"/async/posts/2016/06/23/思考.json","date":1466648660000,"path":{"year":2016,"month":6,"day":23,"name":"思考"},"title":"思考","permalink":"http://catlittlechen.com/2016/06/23/思考/","content":""},{"tags":[{"name":"golang","permalink":"http://catlittlechen.com/tags/golang/","url":"/async/tags/golang.json","count":3}],"categories":[{"name":"golang","permalink":"http://catlittlechen.com/categories/golang/","url":"/async/categories/golang.json","count":3}],"url":"/async/posts/2016/06/20/multinet.json","date":1466402842000,"path":{"year":2016,"month":6,"day":20,"name":"multinet"},"title":"multinet","permalink":"http://catlittlechen.com/2016/06/20/multinet/","content":""}]}